plotlyPowerpoint/__init__.py
plotlyPowerpoint/core.py
plotlyPowerpoint/functions/__init__.py
plotlyPowerpoint/functions/dataManipulation.py
plotlyPowerpoint/functions/chart_functions/__init__.py
plotlyPowerpoint/functions/chart_functions/bar.py
plotlyPowerpoint/functions/chart_functions/facetBar.py
plotlyPowerpoint/functions/chart_functions/facetFilledLine.py
plotlyPowerpoint/functions/chart_functions/facetLine.py
plotlyPowerpoint/functions/chart_functions/filledLine.py
plotlyPowerpoint/functions/chart_functions/line.py
plotlyPowerpoint/functions/chart_functions/lineWithHighlight.py
plotlyPowerpoint-1.3.39.dist-info/LICENSE
plotlyPowerpoint-1.3.39.dist-info/METADATA
plotlyPowerpoint-1.3.39.dist-info/WHEEL
plotlyPowerpoint-1.3.39.dist-info/top_level.txt
plotlyPowerpoint-1.3.39.dist-info/RECORD
