Metadata-Version: 2.1
Name: plotlyPowerpoint
Version: 1.3.39
Summary: A library using Plotly and Powerpoint to easily generate slides with plotly charts in them
Home-page: https://github.com/jonboone1/plotlyPowerpoint
Author: Jon Boone
Author-email: jonboone1@gmail.com
Classifier: Programming Language :: Python :: 3
Classifier: License :: OSI Approved :: MIT License
Classifier: Operating System :: OS Independent
Requires-Python: >=3.6
License-File: LICENSE
Requires-Dist: pandas >=1.2.4
Requires-Dist: plotly >=4.14.3
Requires-Dist: numerize >=0.12
Requires-Dist: scipy >=1.6.3
Requires-Dist: behave >=1.2.5
Requires-Dist: flake8 >=2.0
Requires-Dist: lxml >=3.1.0
Requires-Dist: mock >=1.0.1
Requires-Dist: Pillow >=3.3.2
Requires-Dist: pyparsing >=2.0.1
Requires-Dist: pytest >=2.5
Requires-Dist: XlsxWriter >=0.5.7
Requires-Dist: python-pptx ==0.6.19
